boxcat/Either.py
boxcat/Option.py
boxcat/ProductOpt.py
boxcat/ProductSeq.py
boxcat/Seq.py
boxcat/__init__.py
boxcat-0.0.16.dist-info/LICENSE
boxcat-0.0.16.dist-info/METADATA
boxcat-0.0.16.dist-info/WHEEL
boxcat-0.0.16.dist-info/entry_points.txt
boxcat-0.0.16.dist-info/top_level.txt
boxcat-0.0.16.dist-info/RECORD
