Metadata-Version: 2.1
Name: boxcat
Version: 0.0.16
Summary: A small library to test github actions and using some dodgy fp in Python
Home-page: https://github.com/mywyau/boxcat
Author: Michael Yau
Author-email: mywyau@gmail.com.com
License: UNKNOWN
Platform: UNKNOWN
Classifier: Programming Language :: Python :: 3
Classifier: License :: OSI Approved :: MIT License
Classifier: Operating System :: OS Independent
Requires-Python: >=3.8
License-File: LICENSE
